MANIFEST.in
README.txt
setup.py
link_analyze/__init__.py
link_analyze/analyzer.py
link_analyze/httprequestsniffer.py
link_analyze/logger.py
link_analyze/main.py
link_analyze/monitor.py
link_analyze/reporter.py
link_analyze/util.py
link_analyze/browser/mac/geckodriver
link_analyze/site_module/__init__.py
link_analyze/site_module/module_chain.py
link_analyze/site_module/site_suite.py
madai_link_analyze.egg-info/PKG-INFO
madai_link_analyze.egg-info/SOURCES.txt
madai_link_analyze.egg-info/dependency_links.txt
madai_link_analyze.egg-info/entry_points.txt
madai_link_analyze.egg-info/requires.txt
madai_link_analyze.egg-info/top_level.txt